{"result":[{"dynasty":"东晋","end":"420","label":"东晋","monarchName":"","reignTitle":"","uri":"http://data.library.sh.cn/authority/temporal/21lxcapqduaqmaif","begin":"317","monarch":""},{"dynasty":"东晋","end":"318","label":"东晋建武","monarchName":"司马睿","reignTitle":"建武","uri":"http://data.library.sh.cn/authority/temporal/sorb1srfi8kq7e5t","begin":"317","monarch":"元帝"},{"dynasty":"东晋","end":"322","label":"东晋大兴","monarchName":"司马睿","reignTitle":"大兴;太兴","uri":"http://data.library.sh.cn/authority/temporal/x1cum2fq46fuhfit","begin":"318","monarch":"元帝"},{"dynasty":"东晋","end":"323","label":"东晋永昌","monarchName":"司马绍","reignTitle":"永昌","uri":"http://data.library.sh.cn/authority/temporal/qhohfgha7bvmaf6z","begin":"322","monarch":"明帝"},{"dynasty":"东晋","end":"326","label":"东晋太宁","monarchName":"司马绍","reignTitle":"太宁","uri":"http://data.library.sh.cn/authority/temporal/ely7gzcezjov46mc","begin":"323","monarch":"明帝"},{"dynasty":"东晋","end":"334","label":"东晋咸和","monarchName":"司马衍","reignTitle":"咸和","uri":"http://data.library.sh.cn/authority/temporal/iep9tgbt6luxvlls","begin":"326","monarch":"成帝"},{"dynasty":"东晋","end":"342","label":"东晋咸康","monarchName":"司马衍","reignTitle":"咸康","uri":"http://data.library.sh.cn/authority/temporal/vvkplq2nnkszt31k","begin":"335","monarch":"成帝"},{"dynasty":"东晋","end":"344","label":"东晋建元","monarchName":"司马岳","reignTitle":"建元","uri":"http://data.library.sh.cn/authority/temporal/nrlegpr7vtxqeuux","begin":"343","monarch":"康帝"},{"dynasty":"东晋","end":"356","label":"东晋永和","monarchName":"司马聃","reignTitle":"永和","uri":"http://data.library.sh.cn/authority/temporal/ap4i78hnrysil4il","begin":"345","monarch":"穆帝"},{"dynasty":"东晋","end":"361","label":"东晋升平","monarchName":"司马聃","reignTitle":"升平","uri":"http://data.library.sh.cn/authority/temporal/5agyc1dw9pbqhc8p","begin":"357","monarch":"穆帝"},{"dynasty":"东晋","end":"363","label":"东晋隆和","monarchName":"司马丕","reignTitle":"隆和","uri":"http://data.library.sh.cn/authority/temporal/4a2882kizdby2udi","begin":"362","monarch":"哀帝"},{"dynasty":"东晋","end":"365","label":"东晋兴宁","monarchName":"司马丕","reignTitle":"兴宁","uri":"http://data.library.sh.cn/authority/temporal/y1ytzb8euaiurt8c","begin":"363","monarch":"哀帝"},{"dynasty":"东晋","end":"371","label":"东晋太和","monarchName":"司马奕","reignTitle":"太和","uri":"http://data.library.sh.cn/authority/temporal/v4htuktvexdm3cg8","begin":"366","monarch":"废帝"},{"dynasty":"东晋","end":"372","label":"东晋咸安","monarchName":"司马昱","reignTitle":"咸安","uri":"http://data.library.sh.cn/authority/temporal/6mll8w8vcrvwomwa","begin":"371","monarch":"简文帝"},{"dynasty":"东晋","end":"375","label":"东晋宁康","monarchName":"司马曜","reignTitle":"宁康","uri":"http://data.library.sh.cn/authority/temporal/87957bvxwyd96fpy","begin":"373","monarch":"孝武帝"},{"dynasty":"东晋","end":"396","label":"东晋太元","monarchName":"司马曜","reignTitle":"太元","uri":"http://data.library.sh.cn/authority/temporal/o66peie5uq7orcmy","begin":"376","monarch":"孝武帝"},{"dynasty":"东晋","end":"401","label":"东晋隆安","monarchName":"司马德宗","reignTitle":"隆安","uri":"http://data.library.sh.cn/authority/temporal/9miy4r4uvjbhtfhj","begin":"397","monarch":"安帝"},{"dynasty":"东晋","end":"403","label":"东晋元兴","monarchName":"司马德宗","reignTitle":"元兴","uri":"http://data.library.sh.cn/authority/temporal/7qoibz4hyub5xosg","begin":"402","monarch":"安帝"},{"dynasty":"东晋","end":"403","label":"东晋大亨","monarchName":"司马德宗","reignTitle":"大亨","uri":"http://data.library.sh.cn/authority/temporal/jxbm2w59uwzfejjd","begin":"403","monarch":"安帝"},{"dynasty":"东晋","end":"404","label":"东晋元兴","monarchName":"司马德宗","reignTitle":"元兴","uri":"http://data.library.sh.cn/authority/temporal/mtme6wjkuhvmptxe","begin":"404","monarch":"安帝"},{"dynasty":"东晋","end":"418","label":"东晋义熙","monarchName":"司马德宗","reignTitle":"义熙","uri":"http://data.library.sh.cn/authority/temporal/hmocr5kdvyc1zxkt","begin":"405","monarch":"安帝"},{"dynasty":"胡夏","end":"413","label":"胡夏龙昇","monarchName":"赫连勃勃","reignTitle":"龙昇","uri":"http://data.library.sh.cn/authority/temporal/i7pdzuwk392ajhtb","begin":"407","monarch":""},{"dynasty":"胡夏","end":"418","label":"胡夏凤翔","monarchName":"赫连勃勃","reignTitle":"凤翔","uri":"http://data.library.sh.cn/authority/temporal/aqvtsbdajcpjsi9g","begin":"413","monarch":""},{"dynasty":"胡夏","end":"419","label":"胡夏昌武","monarchName":"赫连勃勃","reignTitle":"昌武","uri":"http://data.library.sh.cn/authority/temporal/kpmfpikv61fjgd3i","begin":"418","monarch":""},{"dynasty":"胡夏","end":"420","label":"胡夏真兴","monarchName":"赫连勃勃","reignTitle":"真兴","uri":"http://data.library.sh.cn/authority/temporal/llccf1uamsi8km69","begin":"419","monarch":""},{"dynasty":"东晋","end":"420","label":"东晋元熙","monarchName":"司马德文","reignTitle":"元熙","uri":"http://data.library.sh.cn/authority/temporal/btouqplmphfzg46v","begin":"419","monarch":"恭帝"},{"dynasty":"胡夏","end":"431","label":"胡夏胜光","monarchName":"赫连定","reignTitle":"胜光","uri":"http://data.library.sh.cn/authority/temporal/y8m25t6dis5wp1mb","begin":"428","monarch":""}]}